{
  "name": "Golem",
  "type": "GOLEM",
  "sprite": "zombie",
  "paletteSwaps": {
    "DARK_BROWN": "DARK_BLUE",
    "DARK_GRAY": "DARK_GRAY",
    "ZOMBIE_SKIN_LIGHT": "DARK_BLUE",
    "ZOMBIE_SKIN_DARK": "DARK_GRAY",
    "BLACK": "BLACK",
    "DARK_RED": "DARK_BLUE",
    "TEAL": "CYAN"
  },
  "startingLife": 120,
  "startingMana": null,
  "startingDamage": 14,
  "lifePerLevel": 0,
  "manaPerLevel": null,
  "damagePerLevel": 0,
  "aiParameters": {
    "speed": 0.9,
    "visionRange": 8,
    "aggressiveness": 0.9,
    "fleeThreshold": 0
  },
  "abilities": {
    "1": ["ATTACK"]
  }
}
